django_sqs_stream/__init__.py
django_sqs_stream/exceptions.py
django_sqs_stream/core/__init__.py
django_sqs_stream/core/constants.py
django_sqs_stream/core/types.py
django_sqs_stream/django_app/__init__.py
django_sqs_stream/django_app/apps.py
django_sqs_stream/django_app/registers.py
django_sqs_stream-0.1.0.dist-info/METADATA
django_sqs_stream-0.1.0.dist-info/WHEEL
django_sqs_stream-0.1.0.dist-info/top_level.txt
django_sqs_stream-0.1.0.dist-info/RECORD
