Metadata-Version: 2.2
Name: django-sqs-stream
Version: 0.1.0
Summary: Add your description here
Requires-Python: >=3.12
Requires-Dist: boto3>=1.36.26
Requires-Dist: cache-register>=0.1.1
Requires-Dist: django>=5.1.6
Requires-Dist: djangorestframework>=3.15.2
